README.md
setup.cfg
setup.py
distributions_yan/Binomialdistribution.py
distributions_yan/Gaussiandistribution.py
distributions_yan/Generaldistribution.py
distributions_yan/__init__.py
distributions_yan.egg-info/PKG-INFO
distributions_yan.egg-info/SOURCES.txt
distributions_yan.egg-info/dependency_links.txt
distributions_yan.egg-info/not-zip-safe
distributions_yan.egg-info/top_level.txt